ruia_shell/__init__.py
ruia_shell/cli.py
ruia_shell/config.py
ruia_shell/shell.py
ruia_shell-0.0.3.dist-info/LICENSE
ruia_shell-0.0.3.dist-info/METADATA
ruia_shell-0.0.3.dist-info/WHEEL
ruia_shell-0.0.3.dist-info/entry_points.txt
ruia_shell-0.0.3.dist-info/top_level.txt
ruia_shell-0.0.3.dist-info/RECORD
