Metadata-Version: 2.1
Name: ruia-shell
Version: 0.0.3
Summary: A Ruia plugin for terminal debugging(IPython)
Home-page: https://github.com/python-ruia/ruia-shell
Author: Howie Hu
Author-email: xiaozizayang@gmail.com
License: UNKNOWN
Platform: UNKNOWN
Requires-Dist: fire
Requires-Dist: ruia (>=0.8.0)
Requires-Dist: ipython
Requires-Dist: nest-asyncio
